latex_merge_changes/__init__.py
latex_merge_changes/__main__.py
latex_merge_changes/cli.py
latex_merge_changes/commands.py
latex_merge_changes/core.py
latex_merge_changes/handlers.py
latex_merge_changes-0.1.0.dist-info/WHEEL
latex_merge_changes-0.1.0.dist-info/entry_points.txt
latex_merge_changes-0.1.0.dist-info/METADATA
latex_merge_changes-0.1.0.dist-info/RECORD
