Metadata-Version: 2.3
Name: latex-merge-changes
Version: 0.1.0
Summary: A tool to accept, reject, or process LaTeX documents using the 'changes' package.
Author: 浩瀚猫
Author-email: 浩瀚猫 <howcanoewang@gmail.com>
License: MIT License
Classifier: Programming Language :: Python :: 3
Classifier: License :: OSI Approved :: GNU General Public License v3 (GPLv3)
Classifier: Operating System :: OS Independent
Classifier: Topic :: Text Processing :: Markup :: LaTeX
Requires-Python: >=3.12
Project-URL: Bug Tracker, https://github.com/your-username/latex-merge-changes/issues
Project-URL: Homepage, https://github.com/your-username/latex-merge-changes
